Workbook

Sheet Sheet1
A1: Month | B1: Transaction Number | C1: Product Code | D1: Product Description | E1: Store Cost | F1: Sale Price | G1: Profit | H1: Commision 10% | I1: Sales Person | J1: Sale Location
A2: Jan | B2: 1001 | C2: 9822 | D2: Pool Cover | E2: 58.3 | F2: 98.4 | I2: Chalie Barns | J2: NM
A3: Jan | B3: 1002 | C3: 2877 | D3: Net | E3: 11.4 | F3: 16.3 | I3: Juan Hernandez | J3: CA
A4: Jan | B4: 1003 | C4: 2499 | D4: 8 ft Hose | E4: 6.2 | F4: 9.2 | I4: Doug Smith | J4: AZ
A5: Jan | B5: 1004 | C5: 8722 | D5: Water Pump | E5: 344 | F5: 502 | I5: Chalie Barns | J5: AZ
A6: Jan | B6: 1005 | C6: 1109 | D6: Chlorine Test Kit | E6: 3 | F6: 8 | I6: Doug Smith | J6: AZ
A7: Jan | B7: 1006 | C7: 9822 | D7: Pool Cover | E7: 58.3 | F7: 98.4 | I7: Doug Smith | J7: AZ
A8: Jan | B8: 1007 | C8: 1109 | D8: Chlorine Test Kit | E8: 3 | F8: 8 | I8: Hellen Johnson | J8: NM
A9: Jan | B9: 1008 | C9: 2877 | D9: Net | E9: 11.4 | F9: 16.3 | I9: Doug Smith | J9: NM
A10: Jan | B10: 1009 | C10: 1109 | D10: Chlorine Test Kit | E10: 3 | F10: 8 | I10: Doug Smith | J10: AZ
A11: Jan | B11: 1010 | C11: 2877 | D11: Net | E11: 11.4 | F11: 16.3 | I11: Juan Hernandez | J11: CO
A12: Jan | B12: 1011 | C12: 2877 | D12: Net | E12: 11.4 | F12: 16.3 | I12: Juan Hernandez | J12: AZ
A13: Jan | B13: 1012 | C13: 4421 | D13: Skimmer | E13: 45 | F13: 87 | I13: Doug Smith | J13: NM
... A172: Dec | B172: 1171 | C172: 4421 | D172: Skimmer | E172: 45 | F172: 87 | I172: Juan Hernandez | J172: NV

Sheet Dataset
A1: Month | B1: Transaction Number | C1: Product Code | D1: Product Description | E1: Store Cost | F1: Sale Price | G1: Profit | H1: COM 10 | I1: Commision 10% | J1: Sales Person | K1: Sale Location
A2: Jan | B2: 1001 | C2: 9822 | D2: Pool Cover | E2: 58.3 | F2: 98.4 | G2: =F2-E2 -> 40.1 | H2: - | I2: =IF(G2>=100,"Yes","-") -> - | J2: Chalie Barns | K2: NM
A3: Jan | B3: 1002 | C3: 2877 | D3: Net | E3: 11.4 | F3: 16.3 | G3: =F3-E3 -> 4.9 | H3: - | I3: =IF(G3>=100,"Yes","-") -> - | J3: Juan Hernandez | K3: CA
A4: Jan | B4: 1003 | C4: 2499 | D4: 8 ft Hose | E4: 6.2 | F4: 9.2 | G4: =F4-E4 -> 3 | H4: - | I4: =IF(G4>=100,"Yes","-") -> - | J4: Doug Smith | K4: AZ | M4: {=_xlfn.UNIQUE(Table1[Sales Person])} -> Chalie Barns
A5: Jan | B5: 1004 | C5: 8722 | D5: Water Pump | E5: 344 | F5: 502 | G5: =F5-E5 -> 158 | H5: Yes | I5: =IF(G5>=100,"Yes","-") -> Yes | J5: Chalie Barns | K5: AZ | M5: Juan Hernandez
A6: Jan | B6: 1005 | C6: 1109 | D6: Chlorine Test Kit | E6: 3 | F6: 8 | G6: =F6-E6 -> 5 | H6: - | I6: =IF(G6>=100,"Yes","-") -> - | J6: Doug Smith | K6: AZ | M6: Doug Smith
A7: Jan | B7: 1006 | C7: 9822 | D7: Pool Cover | E7: 58.3 | F7: 98.4 | G7: =F7-E7 -> 40.1 | H7: - | I7: =IF(G7>=100,"Yes","-") -> - | J7: Doug Smith | K7: AZ | M7: Hellen Johnson
A8: Jan | B8: 1007 | C8: 1109 | D8: Chlorine Test Kit | E8: 3 | F8: 8 | G8: =F8-E8 -> 5 | H8: - | I8: =IF(G8>=100,"Yes","-") -> - | J8: Hellen Johnson | K8: NM
A9: Jan | B9: 1008 | C9: 2877 | D9: Net | E9: 11.4 | F9: 16.3 | G9: =F9-E9 -> 4.9 | H9: - | I9: =IF(G9>=100,"Yes","-") -> - | J9: Doug Smith | K9: NM
A10: Jan | B10: 1009 | C10: 1109 | D10: Chlorine Test Kit | E10: 3 | F10: 8 | G10: =F10-E10 -> 5 | H10: - | I10: =IF(G10>=100,"Yes","-") -> - | J10: Doug Smith | K10: AZ
A11: Jan | B11: 1010 | C11: 2877 | D11: Net | E11: 11.4 | F11: 16.3 | G11: =F11-E11 -> 4.9 | H11: - | I11: =IF(G11>=100,"Yes","-") -> - | J11: Juan Hernandez | K11: CO
A12: Jan | B12: 1011 | C12: 2877 | D12: Net | E12: 11.4 | F12: 16.3 | G12: =F12-E12 -> 4.9 | H12: - | I12: =IF(G12>=100,"Yes","-") -> - | J12: Juan Hernandez | K12: AZ
A13: Jan | B13: 1012 | C13: 4421 | D13: Skimmer | E13: 45 | F13: 87 | G13: =F13-E13 -> 42 | H13: - | I13: =IF(G13>=100,"Yes","-") -> - | J13: Doug Smith | K13: NM
A14: Jan | B14: 1013 | C14: 9212 | D14: 1 Gal Muratic Acid | E14: 4 | F14: 7 | G14: =F14-E14 -> 3 | H14: - | I14: =IF(G14>=100,"Yes","-") -> - | J14: Hellen Johnson | K14: CO
A15: Jan | B15: 1014 | C15: 8722 | D15: Water Pump | E15: 344 | F15: 502 | G15: =F15-E15 -> 158 | H15: Yes | I15: =IF(G15>=100,"Yes","-") -> Yes | J15: Chalie Barns | K15: CA
A16: Jan | B16: 1015 | C16: 2877 | D16: Net | E16: 11.4 | F16: 16.3 | G16: =F16-E16 -> 4.9 | H16: - | I16: =IF(G16>=100,"Yes","-") -> - | J16: Hellen Johnson | K16: AZ
A17: Jan | B17: 1016 | C17: 2499 | D17: 8 ft Hose | E17: 6.2 | F17: 9.2 | G17: =F17-E17 -> 3 | H17: - | I17: =IF(G17>=100,"Yes","-") -> - | J17: Doug Smith | K17: CA
A18: Feb | B18: 1017 | C18: 2242 | D18: AutoVac | E18: 60 | F18: 124 | G18: =F18-E18 -> 64 | H18: - | I18: =IF(G18>=100,"Yes","-") -> - | J18: Juan Hernandez | K18: NM
A19: Feb | B19: 1018 | C19: 1109 | D19: Chlorine Test Kit | E19: 3 | F19: 8 | G19: =F19-E19 -> 5 | H19: - | I19: =IF(G19>=100,"Yes","-") -> - | J19: Doug Smith | K19: CA
... A172: Dec | B172: 1171 | C172: 4421 | D172: Skimmer | E172: 45 | F172: 87 | G172: =F172-E172 -> 42 | H172: - | I172: =IF(G172>=100,"Yes","-") -> - | J172: Juan Hernandez | K172: NV

Sheet pivot analysis
I1: Sales Person | J1: Chalie Barns
B2: Sum of Store Cost | C2: Sum of Sale Price | D2: Sum of Profit
B3: 10753.9 | C3: 17110.6 | D3: 6356.7 | I3: Sum of Profit | J3: Month
I4: Product Description | J4: Jan | K4: Feb | L4: April | M4: June | N4: July | O4: Mar | P4: May | Q4: Aug | R4: Oct | S4: Nov | T4: Dec | U4: Sept | V4: Grand Total
I5: Pool Cover | J5: 40.1 | N5: 40.1 | Q5: 40.1 | U5: 40.1 | V5: 160.4
B6: Sales Person | C6: Count of product sold | D6: Sum of Profit | I6: Net | K6: 4.9 | L6: 4.9 | M6: 4.9 | V6: 14.7
B7: Chalie Barns | C7: 33 | D7: 2015.1 | I7: 8 ft Hose | L7: 3 | M7: 6 | O7: 3 | P7: 3 | V7: 15
B8: Juan Hernandez | C8: 41 | D8: 1021.6 | I8: Water Pump | J8: 316 | K8: 158 | N8: 158 | O8: 158 | Q8: 474 | S8: 158 | U8: 158 | V8: 1580
B9: Doug Smith | C9: 66 | D9: 2235.9 | I9: Chlorine Test Kit | M9: 10 | P9: 5 | V9: 15
B10: Hellen Johnson | C10: 31 | D10: 1084.1 | I10: Skimmer | R10: 42 | T10: 42 | V10: 84
B11: Grand Total | C11: 171 | D11: 6356.7 | I11: 1 Gal Muratic Acid | S11: 3 | V11: 3
I12: AutoVac | L12: 64 | N12: 64 | V12: 128
I13: Algea Killer 8 oz | K13: 5 | M13: 5 | N13: 5 | V13: 15
B14: Sum of Profit | C14: Sales Person | I14: Grand Total | J14: 356.1 | K14: 167.9 | L14: 71.9 | M14: 25.9 | N14: 267.1 | O14: 161 | P14: 8 | Q14: 514.1 | R14: 42 | S14: 161 | T14: 42 | U14: 198.1 | V14: 2015.1
B15: Sale Location | C15: Chalie Barns | D15: Juan Hernandez | E15: Doug Smith | F15: Hellen Johnson | G15: Grand Total
B16: NM | C16: 46.1 | D16: 73.8 | E16: 341.9 | F16: 220 | G16: 681.8
B17: CA | C17: 357.1 | D17: 482.2 | E17: 493.8 | F17: 152 | G17: 1485.1
B18: AZ | C18: 855.9 | D18: 97.8 | E18: 725.3 | F18: 300.1 | G18: 1979.1
B19: CO | C19: 3 | D19: 14.8 | E19: 3 | F19: 3 | G19: 23.8
B20: NV | C20: 526 | D20: 345 | E20: 430.1 | F20: 409 | G20: 1710.1
B21: UT | C21: 227 | D21: 8 | E21: 241.8 | G21: 476.8
B22: Grand Total | C22: 2015.1 | D22: 1021.6 | E22: 2235.9 | F22: 1084.1 | G22: 6356.7

Sheet Calc field
B2: PROFIT PER PERSON
B4: Select Sales person > | C4: Juan Hernandez
B5: Profit | C5: =SUMIF(Table1[Sales Person],'Calc field'!C4,Table1[Profit]) -> 1021.6
B7: TOTAL SALES PER MONTH
C8: {=TRANSPOSE(_xlfn.UNIQUE(Table1[Month]))} -> Jan | D8: Feb | E8: Mar | F8: April | G8: May | H8: June | I8: July | J8: Aug | K8: Sept | L8: Oct | M8: Nov | N8: Dec
B9: {=_xlfn.UNIQUE(Table1[Product Description])} -> Pool Cover | C9: =SUMIFS(Dataset!$G2:$G172,Dataset!$J2:$J172,'Calc field'!$C$4,Dataset!$D2:$D172,'Calc field'!$B9,Dataset!$A2:$A172,'Calc field'!C$8) -> 0 | D9: =SUMIFS(Dataset!$G2:$G172,Dataset!$J2:$J172,'Calc field'!$C$4,Dataset!$D2:$D172,'Calc field'!$B9,Dataset!$A2:$A172,'Calc field'!D$8) -> 40.1 | E9: =SUMIFS(Dataset!$G2:$G172,Dataset!$J2:$J172,'Calc field'!$C$4,Dataset!$D2:$D172,'Calc field'!$B9,Dataset!$A2:$A172,'Calc field'!E$8) -> 0 | F9: =SUMIFS(Dataset!$G2:$G172,Dataset!$J2:$J172,'Calc field'!$C$4,Dataset!$D2:$D172,'Calc field'!$B9,Dataset!$A2:$A172,'Calc field'!F$8) -> 0 | G9: =SUMIFS(Dataset!$G2:$G172,Dataset!$J2:$J172,'Calc field'!$C$4,Dataset!$D2:$D172,'Calc field'!$B9,Dataset!$A2:$A172,'Calc field'!G$8) -> 0 | H9: =SUMIFS(Dataset!$G2:$G172,Dataset!$J2:$J172,'Calc field'!$C$4,Dataset!$D2:$D172,'Calc field'!$B9,Dataset!$A2:$A172,'Calc field'!H$8) -> 0 | I9: =SUMIFS(Dataset!$G2:$G172,Dataset!$J2:$J172,'Calc field'!$C$4,Dataset!$D2:$D172,'Calc field'!$B9,Dataset!$A2:$A172,'Calc field'!I$8) -> 80.2 | J9: =SUMIFS(Dataset!$G2:$G172,Dataset!$J2:$J172,'Calc field'!$C$4,Dataset!$D2:$D172,'Calc field'!$B9,Dataset!$A2:$A172,'Calc field'!J$8) -> 40.1 | ... N9: =SUMIFS(Dataset!$G2:$G172,Dataset!$J2:$J172,'Calc field'!$C$4,Dataset!$D2:$D172,'Calc field'!$B9,Dataset!$A2:$A172,'Calc field'!N$8) -> 0
B10: Net | C10: =SUMIFS(Dataset!$G3:$G173,Dataset!$J3:$J173,'Calc field'!$C$4,Dataset!$D3:$D173,'Calc field'!$B10,Dataset!$A3:$A173,'Calc field'!C$8) -> 14.7 | D10: =SUMIFS(Dataset!$G3:$G173,Dataset!$J3:$J173,'Calc field'!$C$4,Dataset!$D3:$D173,'Calc field'!$B10,Dataset!$A3:$A173,'Calc field'!D$8) -> 4.9 | E10: =SUMIFS(Dataset!$G3:$G173,Dataset!$J3:$J173,'Calc field'!$C$4,Dataset!$D3:$D173,'Calc field'!$B10,Dataset!$A3:$A173,'Calc field'!E$8) -> 4.9 | F10: =SUMIFS(Dataset!$G3:$G173,Dataset!$J3:$J173,'Calc field'!$C$4,Dataset!$D3:$D173,'Calc field'!$B10,Dataset!$A3:$A173,'Calc field'!F$8) -> 0 | G10: =SUMIFS(Dataset!$G3:$G173,Dataset!$J3:$J173,'Calc field'!$C$4,Dataset!$D3:$D173,'Calc field'!$B10,Dataset!$A3:$A173,'Calc field'!G$8) -> 4.9 | H10: =SUMIFS(Dataset!$G3:$G173,Dataset!$J3:$J173,'Calc field'!$C$4,Dataset!$D3:$D173,'Calc field'!$B10,Dataset!$A3:$A173,'Calc field'!H$8) -> 9.8 | I10: =SUMIFS(Dataset!$G3:$G173,Dataset!$J3:$J173,'Calc field'!$C$4,Dataset!$D3:$D173,'Calc field'!$B10,Dataset!$A3:$A173,'Calc field'!I$8) -> 4.9 | J10: =SUMIFS(Dataset!$G3:$G173,Dataset!$J3:$J173,'Calc field'!$C$4,Dataset!$D3:$D173,'Calc field'!$B10,Dataset!$A3:$A173,'Calc field'!J$8) -> 0 | ... N10: =SUMIFS(Dataset!$G3:$G173,Dataset!$J3:$J173,'Calc field'!$C$4,Dataset!$D3:$D173,'Calc field'!$B10,Dataset!$A3:$A173,'Calc field'!N$8) -> 0
B11: 8 ft Hose | C11: =SUMIFS(Dataset!$G4:$G174,Dataset!$J4:$J174,'Calc field'!$C$4,Dataset!$D4:$D174,'Calc field'!$B11,Dataset!$A4:$A174,'Calc field'!C$8) -> 0 | D11: =SUMIFS(Dataset!$G4:$G174,Dataset!$J4:$J174,'Calc field'!$C$4,Dataset!$D4:$D174,'Calc field'!$B11,Dataset!$A4:$A174,'Calc field'!D$8) -> 3 | E11: =SUMIFS(Dataset!$G4:$G174,Dataset!$J4:$J174,'Calc field'!$C$4,Dataset!$D4:$D174,'Calc field'!$B11,Dataset!$A4:$A174,'Calc field'!E$8) -> 6 | F11: =SUMIFS(Dataset!$G4:$G174,Dataset!$J4:$J174,'Calc field'!$C$4,Dataset!$D4:$D174,'Calc field'!$B11,Dataset!$A4:$A174,'Calc field'!F$8) -> 3 | G11: =SUMIFS(Dataset!$G4:$G174,Dataset!$J4:$J174,'Calc field'!$C$4,Dataset!$D4:$D174,'Calc field'!$B11,Dataset!$A4:$A174,'Calc field'!G$8) -> 0 | H11: =SUMIFS(Dataset!$G4:$G174,Dataset!$J4:$J174,'Calc field'!$C$4,Dataset!$D4:$D174,'Calc field'!$B11,Dataset!$A4:$A174,'Calc field'!H$8) -> 0 | I11: =SUMIFS(Dataset!$G4:$G174,Dataset!$J4:$J174,'Calc field'!$C$4,Dataset!$D4:$D174,'Calc field'!$B11,Dataset!$A4:$A174,'Calc field'!I$8) -> 3 | J11: =SUMIFS(Dataset!$G4:$G174,Dataset!$J4:$J174,'Calc field'!$C$4,Dataset!$D4:$D174,'Calc field'!$B11,Dataset!$A4:$A174,'Calc field'!J$8) -> 0 | ... N11: =SUMIFS(Dataset!$G4:$G174,Dataset!$J4:$J174,'Calc field'!$C$4,Dataset!$D4:$D174,'Calc field'!$B11,Dataset!$A4:$A174,'Calc field'!N$8) -> 0
B12: Water Pump | C12: =SUMIFS(Dataset!$G5:$G175,Dataset!$J5:$J175,'Calc field'!$C$4,Dataset!$D5:$D175,'Calc field'!$B12,Dataset!$A5:$A175,'Calc field'!C$8) -> 0 | D12: =SUMIFS(Dataset!$G5:$G175,Dataset!$J5:$J175,'Calc field'!$C$4,Dataset!$D5:$D175,'Calc field'!$B12,Dataset!$A5:$A175,'Calc field'!D$8) -> 0 | E12: =SUMIFS(Dataset!$G5:$G175,Dataset!$J5:$J175,'Calc field'!$C$4,Dataset!$D5:$D175,'Calc field'!$B12,Dataset!$A5:$A175,'Calc field'!E$8) -> 0 | F12: =SUMIFS(Dataset!$G5:$G175,Dataset!$J5:$J175,'Calc field'!$C$4,Dataset!$D5:$D175,'Calc field'!$B12,Dataset!$A5:$A175,'Calc field'!F$8) -> 0 | G12: =SUMIFS(Dataset!$G5:$G175,Dataset!$J5:$J175,'Calc field'!$C$4,Dataset!$D5:$D175,'Calc field'!$B12,Dataset!$A5:$A175,'Calc field'!G$8) -> 0 | H12: =SUMIFS(Dataset!$G5:$G175,Dataset!$J5:$J175,'Calc field'!$C$4,Dataset!$D5:$D175,'Calc field'!$B12,Dataset!$A5:$A175,'Calc field'!H$8) -> 0 | I12: =SUMIFS(Dataset!$G5:$G175,Dataset!$J5:$J175,'Calc field'!$C$4,Dataset!$D5:$D175,'Calc field'!$B12,Dataset!$A5:$A175,'Calc field'!I$8) -> 158 | J12: =SUMIFS(Dataset!$G5:$G175,Dataset!$J5:$J175,'Calc field'!$C$4,Dataset!$D5:$D175,'Calc field'!$B12,Dataset!$A5:$A175,'Calc field'!J$8) -> 0 | ... N12: =SUMIFS(Dataset!$G5:$G175,Dataset!$J5:$J175,'Calc field'!$C$4,Dataset!$D5:$D175,'Calc field'!$B12,Dataset!$A5:$A175,'Calc field'!N$8) -> 0
B13: Chlorine Test Kit | C13: =SUMIFS(Dataset!$G6:$G176,Dataset!$J6:$J176,'Calc field'!$C$4,Dataset!$D6:$D176,'Calc field'!$B13,Dataset!$A6:$A176,'Calc field'!C$8) -> 0 | D13: =SUMIFS(Dataset!$G6:$G176,Dataset!$J6:$J176,'Calc field'!$C$4,Dataset!$D6:$D176,'Calc field'!$B13,Dataset!$A6:$A176,'Calc field'!D$8) -> 10 | E13: =SUMIFS(Dataset!$G6:$G176,Dataset!$J6:$J176,'Calc field'!$C$4,Dataset!$D6:$D176,'Calc field'!$B13,Dataset!$A6:$A176,'Calc field'!E$8) -> 5 | F13: =SUMIFS(Dataset!$G6:$G176,Dataset!$J6:$J176,'Calc field'!$C$4,Dataset!$D6:$D176,'Calc field'!$B13,Dataset!$A6:$A176,'Calc field'!F$8) -> 0 | G13: =SUMIFS(Dataset!$G6:$G176,Dataset!$J6:$J176,'Calc field'!$C$4,Dataset!$D6:$D176,'Calc field'!$B13,Dataset!$A6:$A176,'Calc field'!G$8) -> 5 | H13: =SUMIFS(Dataset!$G6:$G176,Dataset!$J6:$J176,'Calc field'!$C$4,Dataset!$D6:$D176,'Calc field'!$B13,Dataset!$A6:$A176,'Calc field'!H$8) -> 0 | I13: =SUMIFS(Dataset!$G6:$G176,Dataset!$J6:$J176,'Calc field'!$C$4,Dataset!$D6:$D176,'Calc field'!$B13,Dataset!$A6:$A176,'Calc field'!I$8) -> 0 | J13: =SUMIFS(Dataset!$G6:$G176,Dataset!$J6:$J176,'Calc field'!$C$4,Dataset!$D6:$D176,'Calc field'!$B13,Dataset!$A6:$A176,'Calc field'!J$8) -> 0 | ... N13: =SUMIFS(Dataset!$G6:$G176,Dataset!$J6:$J176,'Calc field'!$C$4,Dataset!$D6:$D176,'Calc field'!$B13,Dataset!$A6:$A176,'Calc field'!N$8) -> 0
B14: Skimmer | C14: =SUMIFS(Dataset!$G7:$G177,Dataset!$J7:$J177,'Calc field'!$C$4,Dataset!$D7:$D177,'Calc field'!$B14,Dataset!$A7:$A177,'Calc field'!C$8) -> 0 | D14: =SUMIFS(Dataset!$G7:$G177,Dataset!$J7:$J177,'Calc field'!$C$4,Dataset!$D7:$D177,'Calc field'!$B14,Dataset!$A7:$A177,'Calc field'!D$8) -> 42 | E14: =SUMIFS(Dataset!$G7:$G177,Dataset!$J7:$J177,'Calc field'!$C$4,Dataset!$D7:$D177,'Calc field'!$B14,Dataset!$A7:$A177,'Calc field'!E$8) -> 0 | F14: =SUMIFS(Dataset!$G7:$G177,Dataset!$J7:$J177,'Calc field'!$C$4,Dataset!$D7:$D177,'Calc field'!$B14,Dataset!$A7:$A177,'Calc field'!F$8) -> 0 | G14: =SUMIFS(Dataset!$G7:$G177,Dataset!$J7:$J177,'Calc field'!$C$4,Dataset!$D7:$D177,'Calc field'!$B14,Dataset!$A7:$A177,'Calc field'!G$8) -> 0 | H14: =SUMIFS(Dataset!$G7:$G177,Dataset!$J7:$J177,'Calc field'!$C$4,Dataset!$D7:$D177,'Calc field'!$B14,Dataset!$A7:$A177,'Calc field'!H$8) -> 0 | I14: =SUMIFS(Dataset!$G7:$G177,Dataset!$J7:$J177,'Calc field'!$C$4,Dataset!$D7:$D177,'Calc field'!$B14,Dataset!$A7:$A177,'Calc field'!I$8) -> 0 | J14: =SUMIFS(Dataset!$G7:$G177,Dataset!$J7:$J177,'Calc field'!$C$4,Dataset!$D7:$D177,'Calc field'!$B14,Dataset!$A7:$A177,'Calc field'!J$8) -> 42 | ... N14: =SUMIFS(Dataset!$G7:$G177,Dataset!$J7:$J177,'Calc field'!$C$4,Dataset!$D7:$D177,'Calc field'!$B14,Dataset!$A7:$A177,'Calc field'!N$8) -> 42
B15: 1 Gal Muratic Acid | C15: =SUMIFS(Dataset!$G8:$G178,Dataset!$J8:$J178,'Calc field'!$C$4,Dataset!$D8:$D178,'Calc field'!$B15,Dataset!$A8:$A178,'Calc field'!C$8) -> 0 | D15: =SUMIFS(Dataset!$G8:$G178,Dataset!$J8:$J178,'Calc field'!$C$4,Dataset!$D8:$D178,'Calc field'!$B15,Dataset!$A8:$A178,'Calc field'!D$8) -> 3 | E15: =SUMIFS(Dataset!$G8:$G178,Dataset!$J8:$J178,'Calc field'!$C$4,Dataset!$D8:$D178,'Calc field'!$B15,Dataset!$A8:$A178,'Calc field'!E$8) -> 0 | F15: =SUMIFS(Dataset!$G8:$G178,Dataset!$J8:$J178,'Calc field'!$C$4,Dataset!$D8:$D178,'Calc field'!$B15,Dataset!$A8:$A178,'Calc field'!F$8) -> 0 | G15: =SUMIFS(Dataset!$G8:$G178,Dataset!$J8:$J178,'Calc field'!$C$4,Dataset!$D8:$D178,'Calc field'!$B15,Dataset!$A8:$A178,'Calc field'!G$8) -> 0 | H15: =SUMIFS(Dataset!$G8:$G178,Dataset!$J8:$J178,'Calc field'!$C$4,Dataset!$D8:$D178,'Calc field'!$B15,Dataset!$A8:$A178,'Calc field'!H$8) -> 0 | I15: =SUMIFS(Dataset!$G8:$G178,Dataset!$J8:$J178,'Calc field'!$C$4,Dataset!$D8:$D178,'Calc field'!$B15,Dataset!$A8:$A178,'Calc field'!I$8) -> 0 | J15: =SUMIFS(Dataset!$G8:$G178,Dataset!$J8:$J178,'Calc field'!$C$4,Dataset!$D8:$D178,'Calc field'!$B15,Dataset!$A8:$A178,'Calc field'!J$8) -> 3 | ... N15: =SUMIFS(Dataset!$G8:$G178,Dataset!$J8:$J178,'Calc field'!$C$4,Dataset!$D8:$D178,'Calc field'!$B15,Dataset!$A8:$A178,'Calc field'!N$8) -> 0
B16: AutoVac | C16: =SUMIFS(Dataset!$G9:$G179,Dataset!$J9:$J179,'Calc field'!$C$4,Dataset!$D9:$D179,'Calc field'!$B16,Dataset!$A9:$A179,'Calc field'!C$8) -> 0 | D16: =SUMIFS(Dataset!$G9:$G179,Dataset!$J9:$J179,'Calc field'!$C$4,Dataset!$D9:$D179,'Calc field'!$B16,Dataset!$A9:$A179,'Calc field'!D$8) -> 64 | E16: =SUMIFS(Dataset!$G9:$G179,Dataset!$J9:$J179,'Calc field'!$C$4,Dataset!$D9:$D179,'Calc field'!$B16,Dataset!$A9:$A179,'Calc field'!E$8) -> 0 | F16: =SUMIFS(Dataset!$G9:$G179,Dataset!$J9:$J179,'Calc field'!$C$4,Dataset!$D9:$D179,'Calc field'!$B16,Dataset!$A9:$A179,'Calc field'!F$8) -> 0 | G16: =SUMIFS(Dataset!$G9:$G179,Dataset!$J9:$J179,'Calc field'!$C$4,Dataset!$D9:$D179,'Calc field'!$B16,Dataset!$A9:$A179,'Calc field'!G$8) -> 0 | H16: =SUMIFS(Dataset!$G9:$G179,Dataset!$J9:$J179,'Calc field'!$C$4,Dataset!$D9:$D179,'Calc field'!$B16,Dataset!$A9:$A179,'Calc field'!H$8) -> 0 | I16: =SUMIFS(Dataset!$G9:$G179,Dataset!$J9:$J179,'Calc field'!$C$4,Dataset!$D9:$D179,'Calc field'!$B16,Dataset!$A9:$A179,'Calc field'!I$8) -> 128 | J16: =SUMIFS(Dataset!$G9:$G179,Dataset!$J9:$J179,'Calc field'!$C$4,Dataset!$D9:$D179,'Calc field'!$B16,Dataset!$A9:$A179,'Calc field'!J$8) -> 0 | ... N16: =SUMIFS(Dataset!$G9:$G179,Dataset!$J9:$J179,'Calc field'!$C$4,Dataset!$D9:$D179,'Calc field'!$B16,Dataset!$A9:$A179,'Calc field'!N$8) -> 0
B17: Algea Killer 8 oz | C17: =SUMIFS(Dataset!$G10:$G180,Dataset!$J10:$J180,'Calc field'!$C$4,Dataset!$D10:$D180,'Calc field'!$B17,Dataset!$A10:$A180,'Calc field'!C$8) -> 0 | D17: =SUMIFS(Dataset!$G10:$G180,Dataset!$J10:$J180,'Calc field'!$C$4,Dataset!$D10:$D180,'Calc field'!$B17,Dataset!$A10:$A180,'Calc field'!D$8) -> 0 | E17: =SUMIFS(Dataset!$G10:$G180,Dataset!$J10:$J180,'Calc field'!$C$4,Dataset!$D10:$D180,'Calc field'!$B17,Dataset!$A10:$A180,'Calc field'!E$8) -> 5 | F17: =SUMIFS(Dataset!$G10:$G180,Dataset!$J10:$J180,'Calc field'!$C$4,Dataset!$D10:$D180,'Calc field'!$B17,Dataset!$A10:$A180,'Calc field'!F$8) -> 5 | G17: =SUMIFS(Dataset!$G10:$G180,Dataset!$J10:$J180,'Calc field'!$C$4,Dataset!$D10:$D180,'Calc field'!$B17,Dataset!$A10:$A180,'Calc field'!G$8) -> 5 | H17: =SUMIFS(Dataset!$G10:$G180,Dataset!$J10:$J180,'Calc field'!$C$4,Dataset!$D10:$D180,'Calc field'!$B17,Dataset!$A10:$A180,'Calc field'!H$8) -> 5 | I17: =SUMIFS(Dataset!$G10:$G180,Dataset!$J10:$J180,'Calc field'!$C$4,Dataset!$D10:$D180,'Calc field'!$B17,Dataset!$A10:$A180,'Calc field'!I$8) -> 0 | J17: =SUMIFS(Dataset!$G10:$G180,Dataset!$J10:$J180,'Calc field'!$C$4,Dataset!$D10:$D180,'Calc field'!$B17,Dataset!$A10:$A180,'Calc field'!J$8) -> 0 | ... N17: =SUMIFS(Dataset!$G10:$G180,Dataset!$J10:$J180,'Calc field'!$C$4,Dataset!$D10:$D180,'Calc field'!$B17,Dataset!$A10:$A180,'Calc field'!N$8) -> 0
B18: 5 Gal Chlorine | C18: =SUMIFS(Dataset!$G11:$G181,Dataset!$J11:$J181,'Calc field'!$C$4,Dataset!$D11:$D181,'Calc field'!$B18,Dataset!$A11:$A181,'Calc field'!C$8) -> 0 | D18: =SUMIFS(Dataset!$G11:$G181,Dataset!$J11:$J181,'Calc field'!$C$4,Dataset!$D11:$D181,'Calc field'!$B18,Dataset!$A11:$A181,'Calc field'!D$8) -> 0 | E18: =SUMIFS(Dataset!$G11:$G181,Dataset!$J11:$J181,'Calc field'!$C$4,Dataset!$D11:$D181,'Calc field'!$B18,Dataset!$A11:$A181,'Calc field'!E$8) -> 35 | F18: =SUMIFS(Dataset!$G11:$G181,Dataset!$J11:$J181,'Calc field'!$C$4,Dataset!$D11:$D181,'Calc field'!$B18,Dataset!$A11:$A181,'Calc field'!F$8) -> 0 | G18: =SUMIFS(Dataset!$G11:$G181,Dataset!$J11:$J181,'Calc field'!$C$4,Dataset!$D11:$D181,'Calc field'!$B18,Dataset!$A11:$A181,'Calc field'!G$8) -> 0 | H18: =SUMIFS(Dataset!$G11:$G181,Dataset!$J11:$J181,'Calc field'!$C$4,Dataset!$D11:$D181,'Calc field'!$B18,Dataset!$A11:$A181,'Calc field'!H$8) -> 0 | I18: =SUMIFS(Dataset!$G11:$G181,Dataset!$J11:$J181,'Calc field'!$C$4,Dataset!$D11:$D181,'Calc field'!$B18,Dataset!$A11:$A181,'Calc field'!I$8) -> 0 | J18: =SUMIFS(Dataset!$G11:$G181,Dataset!$J11:$J181,'Calc field'!$C$4,Dataset!$D11:$D181,'Calc field'!$B18,Dataset!$A11:$A181,'Calc field'!J$8) -> 35 | ... N18: =SUMIFS(Dataset!$G11:$G181,Dataset!$J11:$J181,'Calc field'!$C$4,Dataset!$D11:$D181,'Calc field'!$B18,Dataset!$A11:$A181,'Calc field'!N$8) -> 0
B19: TOTAL | C19: =SUM(C9:C18) -> 14.7 | D19: =SUM(D9:D18) -> 167 | E19: =SUM(E9:E18) -> 55.9 | F19: =SUM(F9:F18) -> 8 | G19: =SUM(G9:G18) -> 14.9 | H19: =SUM(H9:H18) -> 14.8 | I19: =SUM(I9:I18) -> 374.1 | J19: =SUM(J9:J18) -> 120.1 | ... N19: =SUM(N9:N18) -> 42
